user_manual/__init__.py
user_manual/user_manual.py
user_manual-1.0.0.dist-info/METADATA
user_manual-1.0.0.dist-info/WHEEL
user_manual-1.0.0.dist-info/entry_points.txt
user_manual-1.0.0.dist-info/top_level.txt
user_manual-1.0.0.dist-info/RECORD
