Metadata-Version: 2.2
Name: user_manual
Version: 1.0.0
Summary: Generate the User Manual by ChatGPT
Home-page: https://github.com/A284viral/protections_v1
Author: Aviral Srivastava
Author-email: aviralsrivastava284@gmail.com
Classifier: Programming Language :: Python :: 3
Classifier: License :: OSI Approved :: MIT License
Classifier: Operating System :: OS Independent
Requires-Python: >=3.6
Requires-Dist: user-manual>=0.0.9
Dynamic: author
Dynamic: author-email
Dynamic: classifier
Dynamic: description-content-type
Dynamic: home-page
Dynamic: requires-dist
Dynamic: requires-python
Dynamic: summary
